[
  {
    "id": "archives-16.1-interviewgaia",
    "type": "article-journal",
    "title": "Street Art and Civic Dialogue: an Interview with Gaia",
    "container-title": "Journal for Cultural & Religious Theory",
    "short-container-title": "JCRT",
    "publisher": "Whitestone Foundation",
    "ISSN": "1530-5228",
    "URL": "https://jcrt.org/archives/16.1/InterviewGaia.pdf",
    "author": [
      {
        "family": "Clay-Robinson",
        "given": "Shelly"
      }
    ],
    "issued": {
      "date-parts": [
        [
          2016
        ]
      ]
    },
    "season": "winter",
    "volume": "16",
    "issue": "1"
  }
]
